{"title":"AIG #7853","mintNo":"#1045","owner":"harry47.arch","ownerProfile":"https://architech.zone/profile/archway13vuu98ygysfe8d847a4zlsds2vuw8q68s9w6s7","image":"https://ipfs.filebase.io/ipfs/QmTsQM8K2HpRuhrmS5ZDUh2NSi7YEBazzLRwAGATvP1SNN","traits":{"background":"Chromatia","lineage":"Grey Ape","tattoos_left":"None","tattoos_right":"None","attire":"Saint Nick's Robes","expression":"Subtle Ember","beard":"Ebony Elegance","earrings":"None","gaze_and_eyewear":"Cosmic Sight","hats_and_hair":"Midnight Cascade","factor":"55"}}