{"title":"AIG #8932","mintNo":"#1068","owner":"archway1nu...qxcdvp","ownerProfile":"https://architech.zone/profile/archway1nu8wusmt0x28e9yaevdkyx07cnwzys8xqxcdvp","image":"https://ipfs.filebase.io/ipfs/QmSbqCVs3Rz3pd5QgKoHEN5NdfG3Admd8sDSg2akaYy8qh","traits":{"background":"Astralush","lineage":"Grey Ape","tattoos_left":"None","tattoos_right":"None","attire":"Musician Ensemble","expression":"Celestial Serenity","beard":"Ebony Elegance","earrings":"None","gaze_and_eyewear":"Cosmic Sight","hats_and_hair":"Midnight Cascade","factor":"55"}}