{"title":"AIG #3925","mintNo":"#1071","owner":"archway1nu...qxcdvp","ownerProfile":"https://architech.zone/profile/archway1nu8wusmt0x28e9yaevdkyx07cnwzys8xqxcdvp","image":"https://ipfs.filebase.io/ipfs/QmPEvky4EQenunUP7rjvz9VCgBJ47MkV19MXMmv1HL968i","traits":{"background":"Luminova","lineage":"Golden Ape","tattoos_left":"None","tattoos_right":"None","attire":"Apelandian Adventure","expression":"Celestial Serenity","beard":"Silver Streak","earrings":"None","gaze_and_eyewear":"Sage's Gaze","hats_and_hair":"Celestial Scholar Cap","factor":"88"}}