{"title":"AIG #9952","mintNo":"#1170","owner":"ang.arch","ownerProfile":"https://architech.zone/profile/archway1whjay3z7ww5zzhydxpt8xffu587jh990pzzkx7","image":"https://ipfs.filebase.io/ipfs/QmXoTxMjgby81UpFPTTz7TV9VpYyDCn7dL6f1NsD4Qh4dn","traits":{"background":"Luminex","lineage":"Grey Ape","tattoos_left":"None","tattoos_right":"None","attire":"Cosmic Party Dress","expression":"Subtle Ember","beard":"Ebony Elegance","earrings":"None","gaze_and_eyewear":"Sage's Gaze","hats_and_hair":"Midnight Cascade","factor":"55"}}