{"title":"AIG #8554","mintNo":"#1206","owner":"archway1uy...mtdmvy","ownerProfile":"https://architech.zone/profile/archway1uyxdrvnmk69m6se8wa2l8ggct94zhlp8mtdmvy","image":"https://ipfs.filebase.io/ipfs/QmU1F4VTDCncavYsY4Be5SLkokoXPC19Xev2HLAgq5gHzT","traits":{"background":"Luminesco","lineage":"Golden Ape","tattoos_left":"None","tattoos_right":"None","attire":"Tourist Outfit","expression":"Celestial Serenity","beard":"Silver Streak","earrings":"None","gaze_and_eyewear":"Stellar Monocle","hats_and_hair":"Ape Safari Hat","factor":"88"}}