{"title":"AIG #1519","mintNo":"#1344","owner":"mjk.arch","ownerProfile":"https://architech.zone/profile/archway1lh6ruf253fhjykdesvfccy0y0vhjque4aenq9h","image":"https://ipfs.filebase.io/ipfs/QmWkJ8i2va33EuafSRUaZxkb4Drd58mpS9RedY9eaH1WD4","traits":{"background":"Stardaze","lineage":"Golden Ape","tattoos_left":"None","tattoos_right":"None","attire":"Apelandian Adventure","expression":"Celestial Serenity","beard":"Silver Streak","earrings":"None","gaze_and_eyewear":"Nebula Shades","hats_and_hair":"Slate Sophistication","factor":"88"}}