{"title":"AIG #9816","mintNo":"#184","owner":"alpha.arch","ownerProfile":"https://architech.zone/profile/archway1tnnhrqpm8rxj7xja5jcu2vmlv2yxz5nalejgq7","image":"https://ipfs.filebase.io/ipfs/QmSnQ3378dLE8n8mZbJpSDT4JFkcnVsnHXpHUdNeK4rpzy","traits":{"background":"Astralush","lineage":"Grey Ape","tattoos_left":"None","tattoos_right":"None","attire":"Cosmic Shirt","expression":"Radiant Joy","beard":"Ebony Elegance","earrings":"None","gaze_and_eyewear":"Enchanted Fatigue","hats_and_hair":"Explorer Hat","factor":"55"}}