{"title":"AIG #6681","mintNo":"#344","owner":"endless.arch","ownerProfile":"https://architech.zone/profile/archway1l72ayh6xpge306s6jwr6l5dflrj35kfkpxx59k","image":"https://ipfs.filebase.io/ipfs/QmRFuUph6MzMQ6QbUiqj1AGLs1cwhutJuJ8pqVgSBfMu9s","traits":{"background":"Chromazia","lineage":"Grey Ape","tattoos_left":"None","tattoos_right":"None","attire":"Explorer Costume","expression":"Radiant Joy","beard":"Ebony Elegance","earrings":"None","gaze_and_eyewear":"Cosmic Sight","hats_and_hair":"Charcoal Charm","factor":"55"}}