{"title":"AIG #5025","mintNo":"#559","owner":"nfts.thephunky1.arch","ownerProfile":"https://architech.zone/profile/archway18s3zsaz5pls3n7kcgkndfqkvhx544cc50ner03","image":"https://ipfs.filebase.io/ipfs/QmWUaYQzCj7PUuSRZthohPChKka7f2vgwSFXExAT7oh7oW","traits":{"background":"Prismatica","lineage":"Golden Ape","tattoos_left":"None","tattoos_right":"None","attire":"Apelandian Adventure","expression":"Celestial Serenity","beard":"Silver Streak","earrings":"None","gaze_and_eyewear":"Stellar Monocle","hats_and_hair":"Onyx Ombre","factor":"88"}}