{"title":"AIG #8275","mintNo":"#64","owner":"donguri.arch","ownerProfile":"https://architech.zone/profile/archway1vemmttg4c0lsqwsdhrjc24ktaahfnh9hjgexvs","image":"https://ipfs.filebase.io/ipfs/QmNNmZUKczoer2HkkG3fZKNApoM5ZMJbHKMCcT9MSqfA5Q","traits":{"background":"Chromazia","lineage":"Grey Ape","tattoos_left":"None","tattoos_right":"None","attire":"Adventure Suit","expression":"Celestial Serenity","beard":"Ebony Elegance","earrings":"None","gaze_and_eyewear":"Enchanted Fatigue","hats_and_hair":"Captain's Cap","factor":"55"}}