{"title":"AIG #5746","mintNo":"#715","owner":"archway1r4...enxp3n","ownerProfile":"https://architech.zone/profile/archway1r4mczz3mp7a290js9jdpyczndr4m76lpenxp3n","image":"https://ipfs.filebase.io/ipfs/QmbR5vRyxY7hFNwZrSexFdfQULkq5qi6GnUyVxQug3brKB","traits":{"background":"Chromatia","lineage":"Grey Ape","tattoos_left":"None","tattoos_right":"None","attire":"Musician Ensemble","expression":"Subtle Ember","beard":"Ebony Elegance","earrings":"None","gaze_and_eyewear":"Sage's Gaze","hats_and_hair":"Silver Streak","factor":"55"}}