{"title":"AIG #5980","mintNo":"#809","owner":"archway1f7...mqyaks","ownerProfile":"https://architech.zone/profile/archway1f79qt9vsg2h4rezul83czusvt5rh0w9zmqyaks","image":"https://ipfs.filebase.io/ipfs/QmPUN7iZ6H9zmyRPFq8bzK3xwfqp6bjfoFB5kT7NVxRyx7","traits":{"background":"Luminesco","lineage":"Golden Ape","tattoos_left":"None","tattoos_right":"None","attire":"Hawaiian Shirt","expression":"Radiant Joy","beard":"Silver Streak","earrings":"None","gaze_and_eyewear":"Stellar Monocle","hats_and_hair":"Slate Sophistication","factor":"88"}}